[{
    "id": 1,
    "name": "Какой ты кот?",
    "rule": {
        "sex": "F",
        "age": "(25, 32)"
    },
    "swap_to_use": "grisha",
    "templates": [{
            "access_key_picture": "4b2de4397cfd3b11c85a080d5c87223e.jpe",
            "text_on_picture": "бизнескот",
            "text": "У тебя есть предпринимательская жилка. Ты можешь поднять инвестиции даже не предоставляя бизнес-плана, ведь твоя мордочка такая милая!"
        },
        {
            "access_key_picture": "e1d7969e73f24d38fb78b0a8c9451b24.jpe",
            "text_on_picture": "кот-король",
            "text": "Люди это лишь твои верные подданные, готовые на все, чтобы ублажить тебя. Но ты их даже не замечаешь за своим величием, давая еще больше поводов для восхищения!"
        },
        {
            "access_key_picture": "3cde12afd403d550a79dfb78e74e9243.png",
            "text_on_picture": "домашний кот",
            "text": "Домашнее тепло и уют -- это про тебя. Твои ласковые мурлыкания никого не оставят равнодушным, а из магазина тебе всегда принесут вкусненькое."
        },
        {
            "access_key_picture": "f794b2f34f3ca4a2feab8f30af6e8fea.jpe",
            "text_on_picture": "ламповый кот",
            "text": "Когда приходят время вечерних ламповых историй, все собираются вокруг тебя, наливают чай и начинают рассказывать байки."
        },
        {
            "access_key_picture": "ca03ea14f8288afd5a30725c6c0991cc.jpe",
            "text_on_picture": "кот-капитошка",
            "text": "Твоя стихия -- это море. Твой путеводель -- это звезды. Шторм и штиль -- лишь испытания твоей мужественности и выдержки."
        }
    ]
}]
